ideal_genom_qc/AncestryQC.py
ideal_genom_qc/Helpers.py
ideal_genom_qc/PopStructure.py
ideal_genom_qc/SampleQC.py
ideal_genom_qc/VariantQC.py
ideal_genom_qc/__init__.py
ideal_genom_qc/__main__.py
ideal_genom_qc/check_tools.py
ideal_genom_qc/get_references.py
ideal_genom_qc-0.2.0.dist-info/LICENSE
ideal_genom_qc-0.2.0.dist-info/METADATA
ideal_genom_qc-0.2.0.dist-info/WHEEL
ideal_genom_qc-0.2.0.dist-info/entry_points.txt
ideal_genom_qc-0.2.0.dist-info/RECORD
