Metadata-Version: 2.3
Name: ideal-genom-qc
Version: 0.2.0
Summary: package to run a genotype quality control pipeline
Author: Luis Giraldo González
Author-email: luisggon@protonmail.com
Requires-Python: >=3.11
Classifier: Programming Language :: Python :: 3
Classifier: License :: OSI Approved :: MIT License
Classifier: Operating System :: OS Independent
Requires-Dist: ipywidgets (>=8.1.5,<9.0.0)
Requires-Dist: jupyter (>=1.1.1,<2.0.0)
Requires-Dist: llvmlite (>=0.43.0,<1.0.0)
Requires-Dist: matplotlib (>=3.8.3,<4.0.0)
Requires-Dist: pandas (>=2.2.1,<3.0.0)
Requires-Dist: psutil (>=5.9.8,<6.0.0)
Requires-Dist: requests (>=2.31.0,<3.0.0)
Requires-Dist: scipy (>=1.12.0,<2.0.0)
Requires-Dist: seaborn (>=0.13.2,<1.0.0)
Requires-Dist: umap-learn (>=0.5.6,<1.0.0)
Project-URL: Homepage, https://github.com/cge-tubingens/cge-comrare-pipeline
Project-URL: Issues, https://github.com/cge-tubingens/cge-comrare-pipeline/issues
